transmit/__init__.py
transmit/client.py
transmit/log.py
transmit/server.py
transmit/trans/__init__.py
transmit/trans/constants.py
transmit/trans/Transmit-remote
transmit/trans/Transmit.py
transmit/trans/ttypes.py
transmit/util.py
transmit-0.4.2.dist-info/METADATA
transmit-0.4.2.dist-info/WHEEL
transmit-0.4.2.dist-info/RECORD
