Metadata-Version: 2.1
Name: transmit
Version: 0.4.2
Summary: Transmit Server & Client use thrift
Home-page: https://github.com/hbh112233abc/py-transmit
License: MIT
Keywords: thrift,transmit,json
Author: hbh112233abc
Author-email: hbh112233abc@163.com
Requires-Python: >=3.7,<4.0
Classifier: License :: OSI Approved :: MIT License
Classifier: Programming Language :: Python :: 3
Classifier: Programming Language :: Python :: 3.7
Classifier: Programming Language :: Python :: 3.8
Classifier: Programming Language :: Python :: 3.9
Classifier: Programming Language :: Python :: 3.10
Classifier: Programming Language :: Python :: 3.11
Classifier: Programming Language :: Python :: 3.12
Requires-Dist: loguru (>=0.7.0,<0.8.0)
Requires-Dist: pydantic (>=2.4.2,<3.0.0)
Requires-Dist: thrift (>=0.21.0,<0.22.0)
Project-URL: Documentation, https://github.com/hbh112233abc/py-transmit
Project-URL: Repository, https://github.com/hbh112233abc/py-transmit
